olsync/__init__.py
olsync/olbrowserlogin.py
olsync/olclient.py
olsync/olsync.py
overleaf_ce_sync-2.0.0.dist-info/entry_points.txt
overleaf_ce_sync-2.0.0.dist-info/WHEEL
overleaf_ce_sync-2.0.0.dist-info/METADATA
overleaf_ce_sync-2.0.0.dist-info/RECORD
