Metadata-Version: 2.1
Name: overleaf-ce-sync
Version: 2.0.0
Summary: Overleaf Two-Way Sync Tool
Home-page: https://github.com/JRodez/overleaf-sync-ce
Keywords: overleaf-ce overleaf sharelatex sync latex tex
Author: jrodez
Author-email: jrodez@users.noreply.github.com
Requires-Python: >=3
Classifier: License :: OSI Approved :: MIT License
Classifier: Intended Audience :: Science/Research
Classifier: Programming Language :: Python :: 3
Requires-Dist: requests == 2.*
Requires-Dist: beautifulsoup4 == 4.11.1
Requires-Dist: yaspin == 2.*
Requires-Dist: python-dateutil~=2.8.1
Requires-Dist: click == 8.*
Requires-Dist: socketIO-client == 0.5.7.2
Requires-Dist: PySide6 == 6.*
